README.md
setup.cfg
setup.py
crispr_cas9/__init__.py
crispr_cas9/count_indels.py
crispr_cas9/create_matrices.py
crispr_cas9/create_plots.py
crispr_cas9.egg-info/PKG-INFO
crispr_cas9.egg-info/SOURCES.txt
crispr_cas9.egg-info/dependency_links.txt
crispr_cas9.egg-info/requires.txt
crispr_cas9.egg-info/top_level.txt