Metadata-Version: 1.1
Name: crispr-cas9
Version: 0.3.4
Summary: script for indels counting in sequencing data
Home-page: https://github.com/babinyurii/crispr_cas9
Author: Yuriy Babin
Author-email: babin.yurii@gmail.com
License: MIT
Download-URL: https://github.com/babinyurii/crispr_cas9/archive/refs/tags/v_0.3.4.tar.gz
Keywords: bioinformatics,indels,sequencing,NGS
Platform: UNKNOWN
Classifier: Development Status :: 4 - Beta
Classifier: Intended Audience :: Developers
Classifier: Topic :: Software Development :: Build Tools
Classifier: License :: OSI Approved :: MIT License
Classifier: Programming Language :: Python :: 3
Classifier: Programming Language :: Python :: 3.4
Classifier: Programming Language :: Python :: 3.5
Classifier: Programming Language :: Python :: 3.6
